pyhwschema/__init__.py
pyhwschema/avrotospark.py
pyhwschema/connection.py
pyhwschema/schema.py
pyhwschema-0.0.5.dist-info/LICENSE
pyhwschema-0.0.5.dist-info/METADATA
pyhwschema-0.0.5.dist-info/WHEEL
pyhwschema-0.0.5.dist-info/top_level.txt
pyhwschema-0.0.5.dist-info/RECORD
