Metadata-Version: 2.1
Name: pyhwschema
Version: 0.0.5
Summary: Python API for Hortonworks Schema Registry
Home-page: https://github.com/kentore82/pyhwschema
Author: Ken Tore Tallakstad
Author-email: tallakstad@gmail.com
License: MIT License
Requires-Dist: avro
Requires-Dist: requests
